{
  "project_info": {
    "project_number": "884752683771",
    "project_id": "disease-detector-doc",
    "storage_bucket": "disease-detector-doc.appspot.com"
  },
  "client": [
    {
      "client_info": {
        "mobilesdk_app_id": "1:884752683771:android:04f11f0311d6124ab2965e",
        "android_client_info": {
          "package_name": "com.example.doc_backend"
        }
      },
      "oauth_client": [
        {
          "client_id": "884752683771-nppa38c5u3kolg88vm59ro3j76ajpavo.apps.googleusercontent.com",
          "client_type": 3
        }
      ],
      "api_key": [
        {
          "current_key": "AIzaSyDGff-zndISERNia1gZWIBOsf3Bp5_8MTw"
        }
      ],
      "services": {
        "appinvite_service": {
          "other_platform_oauth_client": [
            {
              "client_id": "884752683771-nppa38c5u3kolg88vm59ro3j76ajpavo.apps.googleusercontent.com",
              "client_type": 3
            }
          ]
        }
      }
    }
  ],
  "configuration_version": "1"
}